typing_validation/__init__.py
typing_validation/py.typed
typing_validation/validation.py
typing_validation/validation_failure.py
makkus.typing_validation-1.0.3.dist-info/LICENSE
makkus.typing_validation-1.0.3.dist-info/METADATA
makkus.typing_validation-1.0.3.dist-info/WHEEL
makkus.typing_validation-1.0.3.dist-info/top_level.txt
makkus.typing_validation-1.0.3.dist-info/RECORD
