Metadata-Version: 2.1
Name: makkus.typing-validation
Version: 1.0.3
Summary: Forked from the original author until they incorporate latest fixes; a simple library for runtime type-checking.
Home-page: https://github.com/hashberg-io/typing-validation
Author: hashberg
Author-email: sg495@users.noreply.github.com
Project-URL: Bug Tracker, https://github.com/hashberg-io/typing-validation/issues
Classifier: Development Status :: 4 - Beta
Classifier: Programming Language :: Python :: 3.12
Classifier: Programming Language :: Python :: 3.11
Classifier: Programming Language :: Python :: 3.10
Classifier: Programming Language :: Python :: 3.9
Classifier: Programming Language :: Python :: 3.8
Classifier: Programming Language :: Python :: 3.7
Classifier: Operating System :: OS Independent
Classifier: Natural Language :: English
Classifier: Typing :: Typed
Requires-Python: >=3.8
License-File: LICENSE
Requires-Dist: typing-extensions >=4.6.0
Provides-Extra: dev
Requires-Dist: mypy ; extra == 'dev'
Requires-Dist: pylint ; extra == 'dev'
Requires-Dist: pytest ; extra == 'dev'
Requires-Dist: pytest-cov ; extra == 'dev'
Requires-Dist: rich ; extra == 'dev'
